django_user2mailchimp-1.0.7.dist-info/DESCRIPTION.rst
django_user2mailchimp-1.0.7.dist-info/METADATA
django_user2mailchimp-1.0.7.dist-info/RECORD
django_user2mailchimp-1.0.7.dist-info/WHEEL
django_user2mailchimp-1.0.7.dist-info/metadata.json
django_user2mailchimp-1.0.7.dist-info/top_level.txt
user2mailchimp/__init__.py
user2mailchimp/admin.py
user2mailchimp/apps.py
user2mailchimp/models.py
user2mailchimp/settings.py
user2mailchimp/tests.py
user2mailchimp/views.py
