Metadata-Version: 2.0
Name: django-user2mailchimp
Version: 1.0.7
Summary: Synchronize users to mailing list Mailchimp.
Home-page: https://github.com/treemo/user2mailchimp
Author: Treemo
Author-email: treemo@hotmail.fr
License: BSD License
Platform: UNKNOWN
Classifier: Environment :: Web Environment
Classifier: Framework :: Django
Classifier: Intended Audience :: Developers
Classifier: License :: OSI Approved :: BSD License
Classifier: Operating System :: OS Independent
Classifier: Programming Language :: Python
Classifier: Programming Language :: Python :: 3
Classifier: Programming Language :: Python :: 3.2
Classifier: Programming Language :: Python :: 3.3
Classifier: Topic :: Internet :: WWW/HTTP
Classifier: Topic :: Internet :: WWW/HTTP :: Dynamic Content
Requires-Dist: mailchimp
